superfunctions/__init__.py
superfunctions/db/__init__.py
superfunctions/db/errors.py
superfunctions/db/namespace.py
superfunctions/db/types.py
superfunctions/http/__init__.py
superfunctions/http/types.py
sfns-0.1.0.dist-info/METADATA
sfns-0.1.0.dist-info/WHEEL
sfns-0.1.0.dist-info/RECORD
