Metadata-Version: 2.4
Name: sfns
Version: 0.1.0
Summary: Core abstractions for superfunctions ecosystem - database adapters and HTTP utilities
Project-URL: Documentation, https://docs.superfunctions.dev
Project-URL: Repository, https://github.com/21nCo/super-functions
Project-URL: Issues, https://github.com/21nCo/super-functions/issues
Author-email: 21n <support@superfunctions.dev>
License-Expression: MIT
Keywords: adapter,database,http,sfns,superfunctions,web
Classifier: Development Status :: 3 - Alpha
Classifier: Intended Audience :: Developers
Classifier: License :: OSI Approved :: MIT License
Classifier: Programming Language :: Python :: 3
Classifier: Programming Language :: Python :: 3.10
Classifier: Programming Language :: Python :: 3.11
Classifier: Programming Language :: Python :: 3.12
Classifier: Topic :: Software Development :: Libraries :: Python Modules
Requires-Python: >=3.10
Requires-Dist: pydantic>=2.5.0
Provides-Extra: dev
Requires-Dist: black>=23.11.0; extra == 'dev'
Requires-Dist: httpx>=0.25.0; extra == 'dev'
Requires-Dist: mypy>=1.7.0; extra == 'dev'
Requires-Dist: pytest-asyncio>=0.21.0; extra == 'dev'
Requires-Dist: pytest-cov>=4.1.0; extra == 'dev'
Requires-Dist: pytest>=7.4.0; extra == 'dev'
Requires-Dist: ruff>=0.1.6; extra == 'dev'
